README.md
easyserializer.py
setup.py
easyserializer.egg-info/PKG-INFO
easyserializer.egg-info/SOURCES.txt
easyserializer.egg-info/dependency_links.txt
easyserializer.egg-info/requires.txt
easyserializer.egg-info/top_level.txt