Metadata-Version: 2.1
Name: easyserializer
Version: 0.2.14
Summary: serialize a object | 简易对象序列化工具
Home-page: https://github.com/taojy123/EasySerializer
Author: tao.py
Author-email: taojy123@163.com
Maintainer: tao.py
Maintainer-email: taojy123@163.com
License: MIT License
Platform: all
Classifier: Programming Language :: Python
Classifier: Programming Language :: Python :: Implementation
Classifier: Programming Language :: Python :: 2
Classifier: Programming Language :: Python :: 3
Classifier: Topic :: Software Development :: Libraries
